LICENSE
README.md
setup.py
DigiCoreOdbc.egg-info/PKG-INFO
DigiCoreOdbc.egg-info/SOURCES.txt
DigiCoreOdbc.egg-info/dependency_links.txt
DigiCoreOdbc.egg-info/requires.txt
DigiCoreOdbc.egg-info/top_level.txt
DigiCoreOdbc.egg-info/zip-safe
doocn_mongo/__init__.py
doocn_mongo/core.py
doocn_redis/__init__.py
doocn_redis/core.py
doocn_redis/init.py
doocn_tidb/__init__.py
doocn_tidb/core.py
doocn_tidb/init.py
doocn_tidb/util.py